LICENSE.txt
README.md
setup.py
ember/__init__.py
ember/features.py
ember_mivia.egg-info/PKG-INFO
ember_mivia.egg-info/SOURCES.txt
ember_mivia.egg-info/dependency_links.txt
ember_mivia.egg-info/top_level.txt