Metadata-Version: 2.1
Name: ember-mivia
Version: 0.0.6
Summary: Endgame Malware BEnchmark for Research
Home-page: https://github.com/gparrella12/ember
Author-email: proth@endgame.com
License-File: LICENSE.txt
